notebooks/__init__.py
swatmf/__init__.py
swatmf/analyzer.py
swatmf/apexmf_pst_viz.py
swatmf/cvt_gcm_pcp.py
swatmf/forward_run.py
swatmf/gcm_analysis.py
swatmf/gumu_pst_utils.py
swatmf/handler.py
swatmf/objfns.py
swatmf/pst_utils.py
swatmf/swatmf_par_chg_run.py
swatmf/swatmf_pst_par.py
swatmf/swatmf_pst_stats.py
swatmf/swatmf_pst_utils.py
swatmf/swatmf_scenario_utils.py
swatmf/swatmf_utils.py
swatmf/swatmf_viz.py
swatmf/utils.py
swatmf/version.py
swatmf/hg/__init__.py
swatmf/hg/hg_handler.py
swatmf/hg/viz.py
swatmf/opt_files/Absolute_SWAT_Values.txt
swatmf/opt_files/SUFI2_LH_sample.exe
swatmf/opt_files/Swat_Edit.exe
swatmf/opt_files/beopest64.exe
swatmf/opt_files/i64pest.exe
swatmf/opt_files/i64pwtadj1.exe
swatmf/opt_files/model.in
swatmf/opt_files/pestpp-glm.exe
swatmf/opt_files/pestpp-ies.exe
swatmf/opt_files/pestpp-opt.exe
swatmf/opt_files/pestpp-sen.exe
swatmf/opt_files/swat_pars.db.csv
swatmf/opt_files/swatmf_rel230922.exe
swatmf/utils/__init__.py
swatmf/utils/etc.py
swatmf/utils/mf_configs.py
swatmf/utils/swat_configs.py
swatmf/utils/swat_utils.py
swatmf-1.0.0.dist-info/LICENSE
swatmf-1.0.0.dist-info/METADATA
swatmf-1.0.0.dist-info/WHEEL
swatmf-1.0.0.dist-info/top_level.txt
swatmf-1.0.0.dist-info/RECORD
